wqhelp/__init__.py
wqhelp/wqhelp.py
wqhelp-2.0.0.dist-info/LICENSE
wqhelp-2.0.0.dist-info/METADATA
wqhelp-2.0.0.dist-info/WHEEL
wqhelp-2.0.0.dist-info/entry_points.txt
wqhelp-2.0.0.dist-info/top_level.txt
wqhelp-2.0.0.dist-info/RECORD
