Metadata-Version: 2.1
Name: wqhelp
Version: 2.0.0
Summary: Скрипт для получения информации о квестах в World of Warcraft
Home-page: https://x.com/Lanaev0li
Author: Avinion
Author-email: shizofrin@gmail.com
Classifier: Programming Language :: Python :: 3
Classifier: License :: OSI Approved :: MIT License
Classifier: Operating System :: OS Independent
License-File: LICENSE
Requires-Dist: requests
Requires-Dist: beautifulsoup4
